Metadata-Version: 1.0
Name: pandasvault
Version: 0.0.3
Summary: PandasVault - Advanced Pandas Utilities, Functions and Snippets
Home-page: https://github.com/firmai/pandasvault
Author: snowde
Author-email: d.snow@firmai.org
License: MIT
Platform: UNKNOWN
